sdc_api_py/__init__.py
sdc_api_py/_types/Guild.py
sdc_api_py/_types/Raw.py
sdc_api_py/_types/User.py
sdc_api_py/_types/Warns.py
sdc_api_py/_types/__init__.py
sdc_api_py/classes/Bots.py
sdc_api_py/classes/Lib.py
sdc_api_py/classes/Monitoring.py
sdc_api_py/classes/NikaWarns.py
sdc_api_py/classes/__init__.py
sdc_api_py/classes/extension/__init__.py
sdc_api_py/classes/extension/default_extension.py
sdc_api_py-1.3.8.dist-info/LICENSE
sdc_api_py-1.3.8.dist-info/METADATA
sdc_api_py-1.3.8.dist-info/WHEEL
sdc_api_py-1.3.8.dist-info/top_level.txt
sdc_api_py-1.3.8.dist-info/RECORD
