Metadata-Version: 2.1
Name: sdc-api-py
Version: 1.3.8
Summary: An async wrapper for Server-Discord.Com API
Home-page: https://github.com/TheKing-OfTime/sdc-api.py
Author: TheKingOfTime
Author-email: artem.matvienko0@gmai.com
License: UNKNOWN
Platform: UNKNOWN
Classifier: Programming Language :: Python :: 3
Classifier: License :: OSI Approved :: MIT License
Classifier: Operating System :: OS Independent
Requires-Python: >= 3.7
License-File: LICENSE
